MANIFEST.in
README.txt
setup.py
.settings/org.eclipse.core.resources.prefs
docs/HISTORY.txt
docs/LICENSE.txt
src/stxnext/__init__.py
src/stxnext.varnishpurger.egg-info/PKG-INFO
src/stxnext.varnishpurger.egg-info/SOURCES.txt
src/stxnext.varnishpurger.egg-info/dependency_links.txt
src/stxnext.varnishpurger.egg-info/entry_points.txt
src/stxnext.varnishpurger.egg-info/namespace_packages.txt
src/stxnext.varnishpurger.egg-info/not-zip-safe
src/stxnext.varnishpurger.egg-info/requires.txt
src/stxnext.varnishpurger.egg-info/top_level.txt
src/stxnext/varnishpurger/__init__.py
src/stxnext/varnishpurger/configure.zcml
src/stxnext/varnishpurger/utils.py
src/stxnext/varnishpurger/version.txt
src/stxnext/varnishpurger/browser/__init__.py
src/stxnext/varnishpurger/browser/configure.zcml
src/stxnext/varnishpurger/browser/purge_action.py
src/stxnext/varnishpurger/browser/preferences/__init__.py
src/stxnext/varnishpurger/browser/preferences/configure.zcml
src/stxnext/varnishpurger/browser/preferences/varnish_purge_settings.py
src/stxnext/varnishpurger/browser/resources/varnishpurger_icon.gif
src/stxnext/varnishpurger/locales/varnishpurger.pot
src/stxnext/varnishpurger/locales/pl/LC_MESSAGES/varnishpurger.po
src/stxnext/varnishpurger/profiles/default/actionicons.xml
src/stxnext/varnishpurger/profiles/default/actions.xml
src/stxnext/varnishpurger/profiles/default/controlpanel.xml
src/stxnext/varnishpurger/profiles/default/propertiestool.xml