Metadata-Version: 1.0
Name: stxnext.varnishpurger
Version: 0.3.0
Summary: Plone viewlet for purging varnish cache for given url.
Home-page: UNKNOWN
Author: STX Next Sp. z o.o, Radek Jankiewicz, Marcin Ossowski, Wojciech Lichota
Author-email: info@stxnext.pl
License: Zope Public License, Version 2.1 (ZPL)
Keywords: python plone varnish purge
Platform: any
Classifier: Framework :: Zope2
Classifier: Framework :: Plone
Classifier: Intended Audience :: Developers
Classifier: License :: OSI Approved :: Zope Public License
Classifier: Natural Language :: English
Classifier: Programming Language :: Python
